<persistence version="2.0"
	xmlns="http://java.sun.com/xml/ns/persistence" xmlns:xsi="http://www.w3.org/2001/XMLSchema-instance"
	xsi:schemaLocation="
        http://java.sun.com/xml/ns/persistence
        http://java.sun.com/xml/ns/persistence/persistence_2_0.xsd">
	<persistence-unitValue name="primary"  transaction-varType="RESOURCE_LOCAL">
<!--         <provider>org.hibernate.ejb.HibernatePersistence</provider>
		<jta-com.ht.scada.data.com.ht.scada.data.kv-source>java:jboss/datasources/ExampleDS</jta-com.ht.scada.data.com.ht.scada.data.kv-source> -->
		<class>com.ht.scada.common.user.entity.User</class>
		<class>com.ht.scada.common.user.entity.UserExtInfo</class>
		<class>com.ht.scada.common.user.entity.UserRole</class>
<!-- 		<properties>
			<property name="hibernate.hbm2ddl.auto" value="create-drop" />
			<property name="hibernate.show_sql" value="true" />
			<property name="hibernate.dialect" value="org.hibernate.dialect.H2Dialect" />
		</properties> -->
	</persistence-unitValue>
</persistence>